odoo/addons/l10n_ro_stock_account_landed_cost/README.rst
odoo/addons/l10n_ro_stock_account_landed_cost/__init__.py
odoo/addons/l10n_ro_stock_account_landed_cost/__manifest__.py
odoo/addons/l10n_ro_stock_account_landed_cost/i18n/l10n_ro_stock_account.pot
odoo/addons/l10n_ro_stock_account_landed_cost/i18n/l10n_ro_stock_account_landed_cost.pot
odoo/addons/l10n_ro_stock_account_landed_cost/i18n/ro.po
odoo/addons/l10n_ro_stock_account_landed_cost/models/__init__.py
odoo/addons/l10n_ro_stock_account_landed_cost/models/account_move.py
odoo/addons/l10n_ro_stock_account_landed_cost/models/stock_landed_cost.py
odoo/addons/l10n_ro_stock_account_landed_cost/models/stock_move.py
odoo/addons/l10n_ro_stock_account_landed_cost/readme/CONTRIBUTORS.md
odoo/addons/l10n_ro_stock_account_landed_cost/readme/DESCRIPTION.md
odoo/addons/l10n_ro_stock_account_landed_cost/security/ir.model.access.csv
odoo/addons/l10n_ro_stock_account_landed_cost/static/description/icon.png
odoo/addons/l10n_ro_stock_account_landed_cost/static/description/index.html
odoo/addons/l10n_ro_stock_account_landed_cost/tests/__init__.py
odoo/addons/l10n_ro_stock_account_landed_cost/tests/test_ro_stock_avg.py
odoo/addons/l10n_ro_stock_account_landed_cost/tests/test_ro_stock_fifo.py
odoo/addons/l10n_ro_stock_account_landed_cost/tests/test_stock_fifo_internal_transfer.py
odoo/addons/l10n_ro_stock_account_landed_cost/tests/cases/test_cases_avg.csv
odoo/addons/l10n_ro_stock_account_landed_cost/tests/cases/test_cases_fifo.csv
odoo/addons/l10n_ro_stock_account_landed_cost/views/stock_landed_cost_view.xml
odoo_addon_l10n_ro_stock_account_landed_cost-19.0.1.5.0.dist-info/METADATA
odoo_addon_l10n_ro_stock_account_landed_cost-19.0.1.5.0.dist-info/WHEEL
odoo_addon_l10n_ro_stock_account_landed_cost-19.0.1.5.0.dist-info/top_level.txt
odoo_addon_l10n_ro_stock_account_landed_cost-19.0.1.5.0.dist-info/RECORD
